commonroad_labeling/__init__.py
commonroad_labeling/common/__init__.py
commonroad_labeling/common/general.py
commonroad_labeling/common/tag.py
commonroad_labeling/common/util.py
commonroad_labeling/criticality/__init__.py
commonroad_labeling/criticality/analyzer/__init__.py
commonroad_labeling/criticality/analyzer/cm_analyzer.py
commonroad_labeling/criticality/computer/__init__.py
commonroad_labeling/criticality/computer/cm_computer.py
commonroad_labeling/criticality/computer/crit_util.py
commonroad_labeling/criticality/input_output/__init__.py
commonroad_labeling/criticality/input_output/crime_output.py
commonroad_labeling/criticality/trajectory_inserter/__init__.py
commonroad_labeling/criticality/trajectory_inserter/trajectory_inserter.py
commonroad_labeling/ego_vehicle_goal/__init__.py
commonroad_labeling/ego_vehicle_goal/ego_vehicle_goal_intersection.py
commonroad_labeling/road_configuration/__init__.py
commonroad_labeling/road_configuration/route/__init__.py
commonroad_labeling/road_configuration/route/route_lanelet_layout.py
commonroad_labeling/road_configuration/route/route_obstacle.py
commonroad_labeling/road_configuration/route/route_traffic_sign.py
commonroad_labeling/road_configuration/scenario/__init__.py
commonroad_labeling/road_configuration/scenario/scenario_lanelet_layout.py
commonroad_labeling/road_configuration/scenario/scenario_obstacle.py
commonroad_labeling/road_configuration/scenario/scenario_traffic_sign.py
commonroad_labeling/util_tests.py
scripts/criticality_analyzer_usage.py
scripts/criticality_computer_usage.py
scripts/usage.py
commonroad_labeling-2025.1.2.dist-info/METADATA
commonroad_labeling-2025.1.2.dist-info/WHEEL
commonroad_labeling-2025.1.2.dist-info/licenses/LICENSE.txt
commonroad_labeling-2025.1.2.dist-info/RECORD
