Metadata-Version: 2.4
Name: commonroad-labeling
Version: 2025.1.2
Summary: Automatic labeling of CommonRoad scenarios.
License-Expression: BSD-3-Clause
License-File: LICENSE.txt
Author: Florian Finkeldei
Author-email: florian.finkeldei@tum.de
Requires-Python: >=3.10
Classifier: Programming Language :: Python :: 3
Classifier: Programming Language :: Python :: 3.10
Classifier: Programming Language :: Python :: 3.11
Requires-Dist: commonroad-crime (>=0.4.4)
Requires-Dist: commonroad-io (>=2024.3)
Requires-Dist: commonroad-reactive-planner (>=2025.1,<2026.0)
Requires-Dist: commonroad-route-planner (>=2025.1.0)
Requires-Dist: pandas (>=2.2.2,<3.0.0)
Requires-Dist: scikit-learn (>=1.4,<2.0)
Project-URL: Documentation, https://cps.pages.gitlab.lrz.de/commonroad/automatic-scenario-labeling
